drytoml/__init__.py
drytoml/__main__.py
drytoml/app/__init__.py
drytoml/app/cache.py
drytoml/app/explain.py
drytoml/app/export.py
drytoml/app/wrappers.py
drytoml/locate.py
drytoml/merge.py
drytoml/parser.py
drytoml/paths.py
drytoml/types.py
drytoml/utils.py
drytoml-0.2.8.dist-info/entry_points.txt
drytoml-0.2.8.dist-info/LICENSE
drytoml-0.2.8.dist-info/WHEEL
drytoml-0.2.8.dist-info/METADATA
drytoml-0.2.8.dist-info/RECORD
