Metadata-Version: 2.1
Name: drytoml
Version: 0.2.8
Summary: Keep toml configuration centralized and personalizable
Home-page: https://github.com/pwoolvett/drytoml
License: Unlicense
Author: Pablo Woolvett
Author-email: pablowoolvett@gmail.com
Requires-Python: >=3.6.9,<4.0.0
Classifier: License :: Other/Proprietary License
Classifier: Programming Language :: Python :: 3
Classifier: Programming Language :: Python :: 3.7
Classifier: Programming Language :: Python :: 3.8
Classifier: Programming Language :: Python :: 3.9
Provides-Extra: all
Provides-Extra: black
Provides-Extra: dev
Provides-Extra: docs
Provides-Extra: flakehell
Provides-Extra: format
Provides-Extra: isort
Provides-Extra: lint
Provides-Extra: test
Requires-Dist: Sphinx (>=3.4.3,<4.0.0); extra == "docs" or extra == "dev"
Requires-Dist: black (>=20.8b1,<21.0); extra == "black" or extra == "all" or extra == "format" or extra == "lint" or extra == "dev"
Requires-Dist: commitizen (>=2.14.2,<3.0.0); extra == "dev"
Requires-Dist: darglint (>=1.6.0,<2.0.0); extra == "lint" or extra == "dev"
Requires-Dist: fire (>=0.4.0,<0.5.0)
Requires-Dist: flake8-bandit (>=2.1.2,<3.0.0); extra == "lint" or extra == "dev"
Requires-Dist: flake8-bugbear (>=20.11.1,<21.0.0); extra == "lint" or extra == "dev"
Requires-Dist: flake8-builtins (>=1.5.3,<2.0.0); extra == "lint" or extra == "dev"
Requires-Dist: flake8-comprehensions (>=3.3.1,<4.0.0); extra == "lint" or extra == "dev"
Requires-Dist: flake8-debugger (>=4.0.0,<5.0.0); extra == "lint" or extra == "dev"
Requires-Dist: flake8-docstrings (>=1.5.0,<2.0.0); extra == "lint" or extra == "dev"
Requires-Dist: flake8-eradicate (>=1.0.0,<2.0.0); extra == "lint" or extra == "dev"
Requires-Dist: flake8-mutable (>=1.2.0,<2.0.0); extra == "lint" or extra == "dev"
Requires-Dist: flake8-pytest-style (>=1.3.0,<2.0.0); extra == "lint" or extra == "dev"
Requires-Dist: flakeheaven (>=0.10.0-alpha.0,<0.11.0); extra == "flakehell" or extra == "all" or extra == "lint" or extra == "dev"
Requires-Dist: isort (>=5.7.0,<6.0.0); extra == "isort" or extra == "all" or extra == "format" or extra == "lint" or extra == "dev"
Requires-Dist: m2r2 (>=0.2.7,<0.3.0); extra == "docs" or extra == "dev"
Requires-Dist: pep8-naming (>=0.11.1,<0.12.0); extra == "lint" or extra == "dev"
Requires-Dist: pre-commit (>=2.10.1,<3.0.0); extra == "dev"
Requires-Dist: pylint (>=2.6.0,<3.0.0); extra == "lint" or extra == "dev"
Requires-Dist: pytest (>=6.2.2,<7.0.0); extra == "lint" or extra == "test" or extra == "dev"
Requires-Dist: pytest-cov (>=2.11.1,<3.0.0); extra == "test" or extra == "dev"
Requires-Dist: pytest-html (>=3.1.1,<4.0.0); extra == "test" or extra == "dev"
Requires-Dist: recommonmark (>=0.7.1,<0.8.0); extra == "docs" or extra == "dev"
Requires-Dist: sphinx-rtd-theme (>=0.5.1,<0.6.0); extra == "docs" or extra == "dev"
Requires-Dist: tomlkit (>=0.7.0,<0.8.0)
Project-URL: Documentation, https://drytoml.readthedocs.io
Project-URL: Repository, https://github.com/pwoolvett/drytoml
